{
    "main_options": {
        "ingredient_1": {
            "name": "minecraft:rotten_flesh",
            "output_name": "drop_rotten_flesh"
        },
        "ingredient_2": {
            "name": "minecraft:lapis_lazuli",
            "output_name": "drop_lapis_lazuli"
        },
        "stored_enchantments_id": "minecraft:smite"
    },
    "books": [
        {
            "name": "Smite I",
            "ingredient_1_count": 8,
            "ingredient_2_count": 4,
            "stored_enchantments_lvl": 1
        },
        {
            "name": "Smite II",
            "ingredient_1_count": 16,
            "ingredient_2_count": 8,
            "stored_enchantments_lvl": 2
        },
        {
            "name": "Smite III",
            "ingredient_1_count": 24,
            "ingredient_2_count": 12,
            "stored_enchantments_lvl": 3
        },
        {
            "name": "Smite IV",
            "ingredient_1_count": 32,
            "ingredient_2_count": 16,
            "stored_enchantments_lvl": 4
        }
    ]
}